wonderbot/opshelper/ad.pyd
wonderbot/opshelper/bdt.pyd
wonderbot/opshelper/partner.pyd
wonderbot/opshelper/qc.pyd
wonderbot.opshelper-0.0.26.dist-info/METADATA
wonderbot.opshelper-0.0.26.dist-info/WHEEL
wonderbot.opshelper-0.0.26.dist-info/top_level.txt
wonderbot.opshelper-0.0.26.dist-info/RECORD
