Metadata-Version: 2.1
Name: wonderbot.opshelper
Version: 0.0.26
Summary: D helper
Home-page: UNKNOWN
Author: wonderbot
Author-email: wonderbot@gmail.com
License: Apache 2.0
Platform: Windows Only
Classifier: Programming Language :: Python :: 3
Classifier: Operating System :: Microsoft :: Windows
Requires-Dist: tdrpa.tdworker
